MANIFEST.in
README.md
setup.py
./README.md
Finance_Seleya.egg-info/PKG-INFO
Finance_Seleya.egg-info/SOURCES.txt
Finance_Seleya.egg-info/dependency_links.txt
Finance_Seleya.egg-info/requires.txt
Finance_Seleya.egg-info/top_level.txt
requirements/py2.txt
requirements/py3.txt
seleya/__init__.py
seleya/seleya.py
seleya/version.py
seleya/Toolset/__init__.py
seleya/Toolset/blob_service.py
seleya/Toolset/calendar.py
seleya/Toolset/file_util.py
seleya/Toolset/translator.py
seleya/Toolset/audit/__init__.py
seleya/Toolset/audit/esg_metrics.py
seleya/Toolset/portfolio/__init__.py
seleya/Toolset/portfolio/esg_metrics.py
seleya/Toolset/tests/__init__.py
seleya/Toolset/tests/runner.py
seleya/Toolset/tests/suite.py
seleya/config/__init__.py
seleya/config/default_config.py
seleya/core/__init__.py
seleya/core/env.py
seleya/core/fixes.py
seleya/core/helper.py
seleya/core/parallel.py
seleya/data/__init__.py
seleya/data/DataAPI/__init__.py
seleya/data/DataAPI/version.py
seleya/data/DataAPI/http/ESG.py
seleya/data/DataAPI/http/GD.py
seleya/data/DataAPI/http/SEARCH.py
seleya/data/DataAPI/http/USER.py
seleya/data/DataAPI/http/__init__.py
seleya/data/DataAPI/http/utils.py
seleya/data/DataAPI/mongo/__init__.py
seleya/data/DataAPI/mongo/fetch_engine.py
seleya/data/DataAPI/mongo/mongodb.py
seleya/data/DataAPI/sqlatom/__init__.py
seleya/data/DataAPI/sqlatom/db_factory.py
seleya/data/DataAPI/sqlatom/fetch_engine.py
seleya/data/DataAPI/sqlatom/sly/__init__.py
seleya/data/DataAPI/sqlatom/sly/sly_engine.py
seleya/data/SurfaceAPI/__init__.py
seleya/data/SurfaceAPI/mongo/__init__.py
seleya/data/SurfaceAPI/mongo/basic.py
seleya/data/SurfaceAPI/mongo/engine.py
seleya/data/SurfaceAPI/mongo/gd_qrank_dist.py
seleya/data/SurfaceAPI/mongo/gd_qrank_raw.py
seleya/data/SurfaceAPI/mongo/gic_dist_level1.py
seleya/data/SurfaceAPI/mongo/non_gic_dist_level1.py
seleya/data/SurfaceAPI/sqlatom/__init__.py
seleya/data/SurfaceAPI/sqlatom/basic.py
seleya/data/SurfaceAPI/sqlatom/company.py
seleya/data/SurfaceAPI/sqlatom/engine.py
seleya/data/SurfaceAPI/sqlatom/feature_importance.py
seleya/data/SurfaceAPI/sqlatom/gd_overview.py
seleya/data/SurfaceAPI/sqlatom/gd_reviews.py
