Metadata-Version: 2.1
Name: Finance-Seleya
Version: 1.3.0
Summary: FinSeleya 1.3.0
Home-page: https://github.com/flaght
Author: flaght
Author-email: flaght@gmail.com
